{
    "list": [
        {
            "C-FGMQ": "C01121"
        },
        {
            "C-FMPA": "C02137"
        },
        {
            "C-FMPB": "C02138"
        },
        {
            "C-FMPE": "C0213B"
        },
        {
            "C-FMPF": "C0213C"
        },
        {
            "C-FMPK": "C02141"
        },
        {
            "C-FMPN": "C02144"
        },
        {
            "C-FMPO": ""
        },
        {
            "C-FMPW": ""
        },
        {
            "C-GFLA": "C052FB"
        },
        {
            "C-GMPE": "C065E3"
        },
        {
            "C-GMPI": "C065E7"
        },
        {
            "C-GMPM": "C065EB"
        },
        {
            "C-GMPP": "C065EE"
        },
        {
            "C-GMPV": "C065F4"
        },
        {
            "C-GMPW": "C065F5"
        },
        {
            "C-GMPX": "C065F6"
        },
        {
            "C-GMPY": "C065F7"
        },
        {
            "C-GMPZ": "C065F8"
        },
        {
            "C-GMPW": "C065F5"
        }
    ]
}
